{
  "accepted": false,
  "candidate": {
    "parameters": {
      "forwardPassMinGain": 7.0,
      "markDistance": 65.0,
      "passChanceDefault": 0.07559999823570251,
      "passChanceForward": 0.15459999442100525,
      "passChancePressured": 0.29809999465942383,
      "passChanceWing": 0.009999999776482582,
      "shootProgressThreshold": 0.8145999908447266,
      "tackleChance": 0.2199999988079071
    }
  },
  "championEpoch": 138,
  "championParameters": {
    "forwardPassMinGain": 5.0,
    "markDistance": 67.0,
    "passChanceDefault": 0.08370000123977661,
    "passChanceForward": 0.15459999442100525,
    "passChancePressured": 0.31869998574256897,
    "passChanceWing": 0.009999999776482582,
    "shootProgressThreshold": 0.8145999908447266,
    "tackleChance": 0.2003999948501587
  },
  "createdAt": "2026-04-30T09:58:23Z",
  "epoch": 147,
  "evaluation": {
    "avgGoals": 11.77,
    "avgOutOfBounds": 0.01,
    "avgPasses": 137.74,
    "avgShots": 37.06,
    "avgTackles": 5.39,
    "baselineAvgGoals": 5.931,
    "candidateAvgGoals": 5.843,
    "candidateWon": false,
    "earlyStop": null,
    "elapsedMs": 284,
    "games": 1000,
    "gamesPerSecond": 3521.13,
    "goalDiff": -88.0,
    "maxGames": 1000,
    "passCompletionRate": 0.912,
    "tackleSuccessRate": 1.0,
    "zScore": -0.465
  },
  "gamesPerEpoch": 1000,
  "name": "epoch-147",
  "opponent": {
    "parameters": {
      "forwardPassMinGain": 5.0,
      "markDistance": 67.0,
      "passChanceDefault": 0.08370000123977661,
      "passChanceForward": 0.15459999442100525,
      "passChancePressured": 0.31869998574256897,
      "passChanceWing": 0.009999999776482582,
      "shootProgressThreshold": 0.8145999908447266,
      "tackleChance": 0.2003999948501587
    },
    "sourceEpoch": 138
  },
  "session": "session-4"
}
