{
  "acceptedCount": 2,
  "acceptedEpochs": [
    1,
    5
  ],
  "averageEpochElapsedMs": 482,
  "bestGoalDiff": 329.0,
  "epochs": 5,
  "finalChampionEpoch": 5,
  "finalChampionPlayerParams": [
    {
      "decisions": {
        "aggression": 1.9529999494552612,
        "forwardPassMinGain": 4.6707000732421875,
        "markDistance": 71.533203125,
        "passChanceDefault": 0.061000000685453415,
        "passChanceForward": 0.026200000196695328,
        "passChancePressured": 0.275299996137619,
        "passChanceWing": 0.2387000024318695,
        "passDirDefensive": 1.1115000247955322,
        "passDirNeutral": 1.4904999732971191,
        "passDirOffensive": 0.6068000197410583,
        "riskAppetite": 0.6776999831199646,
        "shootProgressThreshold": 0.669700026512146,
        "tackleChance": 0.18060000240802765
      },
      "spatial": {
        "ball": {
          "max": 0.0,
          "min": 0.0,
          "preferred": 0.0
        },
        "opponent": {
          "max": 165.6165008544922,
          "min": 40.4822998046875,
          "preferred": 127.40740203857422
        },
        "ownGoal": {
          "max": 816.5689697265625,
          "min": 357.3739013671875,
          "preferred": 728.5028076171875
        },
        "side": {
          "max": 208.46099853515625,
          "min": 84.86920166015625,
          "preferred": 84.86920166015625
        },
        "teammate": {
          "max": 331.4071960449219,
          "min": 205.68820190429688,
          "preferred": 277.79541015625
        }
      }
    },
    {
      "decisions": {
        "aggression": 1.5879000425338745,
        "forwardPassMinGain": 10.500499725341797,
        "markDistance": 25.0,
        "passChanceDefault": 0.09679999947547913,
        "passChanceForward": 0.04639999940991402,
        "passChancePressured": 0.019999999552965164,
        "passChanceWing": 0.057100001722574234,
        "passDirDefensive": 1.807800054550171,
        "passDirNeutral": 0.23109999299049377,
        "passDirOffensive": 2.0,
        "riskAppetite": 0.34310001134872437,
        "shootProgressThreshold": 0.6789000034332275,
        "tackleChance": 0.09030000120401382
      },
      "spatial": {
        "ball": {
          "max": 675.6807861328125,
          "min": 4.54449987411499,
          "preferred": 131.1396942138672
        },
        "opponent": {
          "max": 272.88629150390625,
          "min": 0.0,
          "preferred": 146.93569946289062
        },
        "ownGoal": {
          "max": 347.4309997558594,
          "min": 170.71670532226562,
          "preferred": 326.4783020019531
        },
        "side": {
          "max": 362.92718505859375,
          "min": 71.89920043945312,
          "preferred": 345.44110107421875
        },
        "teammate": {
          "max": 76.02580261230469,
          "min": 62.66389846801758,
          "preferred": 62.66389846801758
        }
      }
    },
    {
      "decisions": {
        "aggression": 1.3066999912261963,
        "forwardPassMinGain": 4.99399995803833,
        "markDistance": 43.14459991455078,
        "passChanceDefault": 0.20000000298023224,
        "passChanceForward": 0.004999999888241291,
        "passChancePressured": 0.37290000915527344,
        "passChanceWing": 0.019099999219179153,
        "passDirDefensive": 1.1710000038146973,
        "passDirNeutral": 0.0,
        "passDirOffensive": 1.0892000198364258,
        "riskAppetite": 0.7267000079154968,
        "shootProgressThreshold": 0.5871000289916992,
        "tackleChance": 0.21739999949932098
      },
      "spatial": {
        "ball": {
          "max": 32.20669937133789,
          "min": 2.7388999462127686,
          "preferred": 6.229100227355957
        },
        "opponent": {
          "max": 41.39950180053711,
          "min": 0.0,
          "preferred": 25.96820068359375
        },
        "ownGoal": {
          "max": 693.5247192382812,
          "min": 12.029199600219727,
          "preferred": 423.7294921875
        },
        "side": {
          "max": 467.3291931152344,
          "min": 378.6777038574219,
          "preferred": 451.33819580078125
        },
        "teammate": {
          "max": 73.51799774169922,
          "min": 7.0594000816345215,
          "preferred": 24.166400909423828
        }
      }
    },
    {
      "decisions": {
        "aggression": 1.4692000150680542,
        "forwardPassMinGain": 15.690899848937988,
        "markDistance": 66.0822982788086,
        "passChanceDefault": 0.15770000219345093,
        "passChanceForward": 0.10769999772310257,
        "passChancePressured": 0.09640000015497208,
        "passChanceWing": 0.010499999858438969,
        "passDirDefensive": 0.1290999948978424,
        "passDirNeutral": 1.3704999685287476,
        "passDirOffensive": 1.7569999694824219,
        "riskAppetite": 0.038100000470876694,
        "shootProgressThreshold": 0.5616000294685364,
        "tackleChance": 0.05660000070929527
      },
      "spatial": {
        "ball": {
          "max": 42.93239974975586,
          "min": 16.554899215698242,
          "preferred": 16.554899215698242
        },
        "opponent": {
          "max": 89.1447982788086,
          "min": 57.206600189208984,
          "preferred": 89.1447982788086
        },
        "ownGoal": {
          "max": 546.12890625,
          "min": 400.8536071777344,
          "preferred": 446.1622009277344
        },
        "side": {
          "max": 304.15380859375,
          "min": 0.0,
          "preferred": 298.748291015625
        },
        "teammate": {
          "max": 119.34269714355469,
          "min": 59.10820007324219,
          "preferred": 59.10820007324219
        }
      }
    },
    {
      "decisions": {
        "aggression": 1.853600025177002,
        "forwardPassMinGain": 2.708199977874756,
        "markDistance": 30.959800720214844,
        "passChanceDefault": 0.12770000100135803,
        "passChanceForward": 0.025800000876188278,
        "passChancePressured": 0.15199999511241913,
        "passChanceWing": 0.17790000140666962,
        "passDirDefensive": 0.6901000142097473,
        "passDirNeutral": 1.3499000072479248,
        "passDirOffensive": 1.254699945449829,
        "riskAppetite": 0.5601999759674072,
        "shootProgressThreshold": 0.8597999811172485,
        "tackleChance": 0.035999998450279236
      },
      "spatial": {
        "ball": {
          "max": 700.0,
          "min": 175.99400329589844,
          "preferred": 371.9466857910156
        },
        "opponent": {
          "max": 299.4902038574219,
          "min": 179.32640075683594,
          "preferred": 207.48260498046875
        },
        "ownGoal": {
          "max": 824.9962158203125,
          "min": 38.91350173950195,
          "preferred": 303.14410400390625
        },
        "side": {
          "max": 309.6658020019531,
          "min": 187.72210693359375,
          "preferred": 249.0272979736328
        },
        "teammate": {
          "max": 400.0,
          "min": 134.59669494628906,
          "preferred": 314.74639892578125
        }
      }
    }
  ],
  "finishedAt": "2026-05-05T07:41:59Z",
  "gamesPerEpoch": 50000,
  "history": [
    {
      "accepted": true,
      "baselineAvgGoals": 9.949,
      "candidateAvgGoals": 10.547,
      "championEpoch": 1,
      "earlyStop": "better",
      "elapsedMs": 1105,
      "epoch": 1,
      "gamesRun": 550,
      "goalDiff": 329.0,
      "zScore": 2.542
    },
    {
      "accepted": false,
      "baselineAvgGoals": 10.342,
      "candidateAvgGoals": 9.606,
      "championEpoch": 1,
      "earlyStop": "worse",
      "elapsedMs": 645,
      "epoch": 2,
      "gamesRun": 325,
      "goalDiff": -239.0,
      "zScore": -2.613
    },
    {
      "accepted": false,
      "baselineAvgGoals": 10.02,
      "candidateAvgGoals": 6.65,
      "championEpoch": 1,
      "earlyStop": "worse",
      "elapsedMs": 203,
      "epoch": 3,
      "gamesRun": 100,
      "goalDiff": -337.0,
      "zScore": -8.252
    },
    {
      "accepted": false,
      "baselineAvgGoals": 10.952,
      "candidateAvgGoals": 9.584,
      "championEpoch": 1,
      "earlyStop": "worse",
      "elapsedMs": 254,
      "epoch": 4,
      "gamesRun": 125,
      "goalDiff": -171.0,
      "zScore": -2.956
    },
    {
      "accepted": true,
      "baselineAvgGoals": 9.45,
      "candidateAvgGoals": 11.13,
      "championEpoch": 5,
      "earlyStop": "better",
      "elapsedMs": 205,
      "epoch": 5,
      "gamesRun": 100,
      "goalDiff": 168.0,
      "zScore": 3.135
    }
  ],
  "name": "anneal-stage-3-5ep-50000g",
  "rejectedCount": 3,
  "startedAt": "2026-05-05T07:41:57Z",
  "totalTrainingElapsedMs": 2412,
  "trainingMode": "v6-team"
}
