{
  "accepted": false,
  "candidate": {
    "playerParams": [
      {
        "aggression": 2.0,
        "base": {
          "forwardPassMinGain": 13.0,
          "markDistance": 50.0,
          "passChanceDefault": 0.07559999823570251,
          "passChanceForward": 0.16369999945163727,
          "passChancePressured": 0.4000000059604645,
          "passChanceWing": 0.14100000262260437,
          "shootProgressThreshold": 0.7505999803543091,
          "tackleChance": 0.2199999988079071
        },
        "blockAvoidance": 0.6170167326927185,
        "blockDistance": 23.65407371520996,
        "chemistryBonus": 0.0,
        "chemistryTargetId": -1,
        "clearShotBonus": 0.006922255735844374,
        "corridorPreference": 1,
        "edgeAvoidance": 0.295477956533432,
        "goalAttraction": 0.11276161670684814,
        "pressureRadius": 91.59837341308594,
        "riskAppetite": 0.3602297604084015,
        "visionRadius": 1000000000.0,
        "zoneAggression": [
          1.2429702281951904,
          0.7505735158920288,
          1.5533382892608643,
          0.6469164490699768,
          0.8818357586860657
        ]
      },
      {
        "aggression": 0.5880041718482971,
        "base": {
          "forwardPassMinGain": 18.0,
          "markDistance": 61.0,
          "passChanceDefault": 0.004999999888241291,
          "passChanceForward": 0.18000000715255737,
          "passChancePressured": 0.4000000059604645,
          "passChanceWing": 0.009999999776482582,
          "shootProgressThreshold": 0.8162999749183655,
          "tackleChance": 0.2199999988079071
        },
        "blockAvoidance": 0.33595559000968933,
        "blockDistance": 23.293792724609375,
        "chemistryBonus": 0.0,
        "chemistryTargetId": -1,
        "clearShotBonus": 0.06375373154878616,
        "corridorPreference": 0,
        "edgeAvoidance": 0.011147676967084408,
        "goalAttraction": 0.26878899335861206,
        "pressureRadius": 95.31826782226562,
        "riskAppetite": 0.6113166809082031,
        "visionRadius": 1000000000.0,
        "zoneAggression": [
          0.8120741844177246,
          0.9085901379585266,
          0.9310086369514465,
          1.2150455713272095,
          1.1601442098617554
        ]
      },
      {
        "aggression": 1.872754693031311,
        "base": {
          "forwardPassMinGain": 18.0,
          "markDistance": 74.0,
          "passChanceDefault": 0.004999999888241291,
          "passChanceForward": 0.1599999964237213,
          "passChancePressured": 0.4000000059604645,
          "passChanceWing": 0.009999999776482582,
          "shootProgressThreshold": 0.8125,
          "tackleChance": 0.19050000607967377
        },
        "blockAvoidance": 0.20702996850013733,
        "blockDistance": 28.949831008911133,
        "chemistryBonus": 0.0,
        "chemistryTargetId": -1,
        "clearShotBonus": 0.2869267463684082,
        "corridorPreference": 1,
        "edgeAvoidance": 0.0,
        "goalAttraction": 0.6546172499656677,
        "pressureRadius": 61.78904342651367,
        "riskAppetite": 0.4824705123901367,
        "visionRadius": 1000000000.0,
        "zoneAggression": [
          1.086510419845581,
          1.5088210105895996,
          0.876882791519165,
          0.7904089689254761,
          1.085485816001892
        ]
      },
      {
        "aggression": 1.1845840215682983,
        "base": {
          "forwardPassMinGain": 11.0,
          "markDistance": 76.0,
          "passChanceDefault": 0.13689999282360077,
          "passChanceForward": 0.16009999811649323,
          "passChancePressured": 0.3255999982357025,
          "passChanceWing": 0.009999999776482582,
          "shootProgressThreshold": 0.6836000084877014,
          "tackleChance": 0.10719999670982361
        },
        "blockAvoidance": 0.5181546807289124,
        "blockDistance": 35.2830810546875,
        "chemistryBonus": 0.0,
        "chemistryTargetId": -1,
        "clearShotBonus": 0.17819565534591675,
        "corridorPreference": 0,
        "edgeAvoidance": 0.7821962237358093,
        "goalAttraction": 0.19522592425346375,
        "pressureRadius": 90.59664154052734,
        "riskAppetite": 0.007680416107177734,
        "visionRadius": 1000000000.0,
        "zoneAggression": [
          1.2757760286331177,
          1.0087579488754272,
          0.689176082611084,
          1.4844814538955688,
          0.8029693961143494
        ]
      },
      {
        "aggression": 1.271427869796753,
        "base": {
          "forwardPassMinGain": 14.0,
          "markDistance": 77.0,
          "passChanceDefault": 0.05290000140666962,
          "passChanceForward": 0.1543000042438507,
          "passChancePressured": 0.4000000059604645,
          "passChanceWing": 0.07020000368356705,
          "shootProgressThreshold": 0.8607000112533569,
          "tackleChance": 0.16120000183582306
        },
        "blockAvoidance": 0.6841490864753723,
        "blockDistance": 13.251578330993652,
        "chemistryBonus": 0.0,
        "chemistryTargetId": -1,
        "clearShotBonus": 0.4391512870788574,
        "corridorPreference": -1,
        "edgeAvoidance": 0.5564186573028564,
        "goalAttraction": 0.19854560494422913,
        "pressureRadius": 38.513702392578125,
        "riskAppetite": 0.29490405321121216,
        "visionRadius": 1000000000.0,
        "zoneAggression": [
          1.1172020435333252,
          0.9545609951019287,
          1.1811184883117676,
          1.055994987487793,
          0.7032451629638672
        ]
      }
    ]
  },
  "championEpoch": 71,
  "championPlayerParams": [
    {
      "aggression": 2.0,
      "base": {
        "forwardPassMinGain": 14.0,
        "markDistance": 52.0,
        "passChanceDefault": 0.08349999785423279,
        "passChanceForward": 0.18000000715255737,
        "passChancePressured": 0.4000000059604645,
        "passChanceWing": 0.14100000262260437,
        "shootProgressThreshold": 0.7613000273704529,
        "tackleChance": 0.2199999988079071
      },
      "blockAvoidance": 0.6170167326927185,
      "blockDistance": 23.65407371520996,
      "chemistryBonus": 0.0,
      "chemistryTargetId": -1,
      "clearShotBonus": 0.006922255735844374,
      "corridorPreference": 1,
      "edgeAvoidance": 0.295477956533432,
      "goalAttraction": 0.11276161670684814,
      "pressureRadius": 91.59837341308594,
      "riskAppetite": 0.3602297604084015,
      "visionRadius": 1000000000.0,
      "zoneAggression": [
        1.2429702281951904,
        0.7505735158920288,
        1.3312385082244873,
        0.5696296095848083,
        0.8818357586860657
      ]
    },
    {
      "aggression": 0.7067928910255432,
      "base": {
        "forwardPassMinGain": 15.0,
        "markDistance": 52.0,
        "passChanceDefault": 0.008100000210106373,
        "passChanceForward": 0.1453000009059906,
        "passChancePressured": 0.4000000059604645,
        "passChanceWing": 0.009999999776482582,
        "shootProgressThreshold": 0.8162999749183655,
        "tackleChance": 0.2199999988079071
      },
      "blockAvoidance": 0.37391412258148193,
      "blockDistance": 25.72054672241211,
      "chemistryBonus": 0.0,
      "chemistryTargetId": -1,
      "clearShotBonus": 0.06375373154878616,
      "corridorPreference": 0,
      "edgeAvoidance": 0.0,
      "goalAttraction": 0.26878899335861206,
      "pressureRadius": 95.31826782226562,
      "riskAppetite": 0.5823724269866943,
      "visionRadius": 1000000000.0,
      "zoneAggression": [
        0.8120741844177246,
        0.9085901379585266,
        1.0274022817611694,
        1.1917575597763062,
        1.1601442098617554
      ]
    },
    {
      "aggression": 1.872754693031311,
      "base": {
        "forwardPassMinGain": 18.0,
        "markDistance": 74.0,
        "passChanceDefault": 0.004999999888241291,
        "passChanceForward": 0.1599999964237213,
        "passChancePressured": 0.4000000059604645,
        "passChanceWing": 0.009999999776482582,
        "shootProgressThreshold": 0.8125,
        "tackleChance": 0.19050000607967377
      },
      "blockAvoidance": 0.20702996850013733,
      "blockDistance": 28.949831008911133,
      "chemistryBonus": 0.0,
      "chemistryTargetId": -1,
      "clearShotBonus": 0.2869267463684082,
      "corridorPreference": 1,
      "edgeAvoidance": 0.0,
      "goalAttraction": 0.6546172499656677,
      "pressureRadius": 61.78904342651367,
      "riskAppetite": 0.4824705123901367,
      "visionRadius": 1000000000.0,
      "zoneAggression": [
        1.086510419845581,
        1.5088210105895996,
        0.876882791519165,
        0.7904089689254761,
        1.085485816001892
      ]
    },
    {
      "aggression": 1.1845840215682983,
      "base": {
        "forwardPassMinGain": 11.0,
        "markDistance": 76.0,
        "passChanceDefault": 0.13689999282360077,
        "passChanceForward": 0.16009999811649323,
        "passChancePressured": 0.3255999982357025,
        "passChanceWing": 0.009999999776482582,
        "shootProgressThreshold": 0.6836000084877014,
        "tackleChance": 0.10719999670982361
      },
      "blockAvoidance": 0.5181546807289124,
      "blockDistance": 35.2830810546875,
      "chemistryBonus": 0.0,
      "chemistryTargetId": -1,
      "clearShotBonus": 0.17819565534591675,
      "corridorPreference": 0,
      "edgeAvoidance": 0.7821962237358093,
      "goalAttraction": 0.19522592425346375,
      "pressureRadius": 90.59664154052734,
      "riskAppetite": 0.007680416107177734,
      "visionRadius": 1000000000.0,
      "zoneAggression": [
        1.2757760286331177,
        1.0087579488754272,
        0.689176082611084,
        1.4844814538955688,
        0.8029693961143494
      ]
    },
    {
      "aggression": 1.271427869796753,
      "base": {
        "forwardPassMinGain": 14.0,
        "markDistance": 77.0,
        "passChanceDefault": 0.05290000140666962,
        "passChanceForward": 0.1543000042438507,
        "passChancePressured": 0.4000000059604645,
        "passChanceWing": 0.07020000368356705,
        "shootProgressThreshold": 0.8607000112533569,
        "tackleChance": 0.16120000183582306
      },
      "blockAvoidance": 0.6841490864753723,
      "blockDistance": 13.251578330993652,
      "chemistryBonus": 0.0,
      "chemistryTargetId": -1,
      "clearShotBonus": 0.4391512870788574,
      "corridorPreference": -1,
      "edgeAvoidance": 0.5564186573028564,
      "goalAttraction": 0.19854560494422913,
      "pressureRadius": 38.513702392578125,
      "riskAppetite": 0.29490405321121216,
      "visionRadius": 1000000000.0,
      "zoneAggression": [
        1.1172020435333252,
        0.9545609951019287,
        1.1811184883117676,
        1.055994987487793,
        0.7032451629638672
      ]
    }
  ],
  "createdAt": "2026-05-01T03:21:56Z",
  "epoch": 73,
  "evaluation": {
    "avgGoals": 12.49,
    "avgOutOfBounds": 0.01,
    "avgPasses": 132.64,
    "avgShots": 41.91,
    "avgTackles": 6.0,
    "baselineAvgGoals": 6.375,
    "candidateAvgGoals": 6.111,
    "candidateWon": false,
    "earlyStop": "worse",
    "elapsedMs": 2530,
    "games": 4150,
    "gamesPerSecond": 1640.32,
    "goalDiff": -1095.0,
    "maxGames": 100000,
    "passCompletionRate": 0.901,
    "tackleSuccessRate": 1.0,
    "zScore": -2.501
  },
  "gamesPerEpoch": 100000,
  "mutatedSlots": [
    0,
    1
  ],
  "name": "epoch-073",
  "opponent": {
    "playerParams": [
      {
        "aggression": 2.0,
        "base": {
          "forwardPassMinGain": 14.0,
          "markDistance": 52.0,
          "passChanceDefault": 0.08349999785423279,
          "passChanceForward": 0.18000000715255737,
          "passChancePressured": 0.4000000059604645,
          "passChanceWing": 0.14100000262260437,
          "shootProgressThreshold": 0.7613000273704529,
          "tackleChance": 0.2199999988079071
        },
        "blockAvoidance": 0.6170167326927185,
        "blockDistance": 23.65407371520996,
        "chemistryBonus": 0.0,
        "chemistryTargetId": -1,
        "clearShotBonus": 0.006922255735844374,
        "corridorPreference": 1,
        "edgeAvoidance": 0.295477956533432,
        "goalAttraction": 0.11276161670684814,
        "pressureRadius": 91.59837341308594,
        "riskAppetite": 0.3602297604084015,
        "visionRadius": 1000000000.0,
        "zoneAggression": [
          1.2429702281951904,
          0.7505735158920288,
          1.3312385082244873,
          0.5696296095848083,
          0.8818357586860657
        ]
      },
      {
        "aggression": 0.7067928910255432,
        "base": {
          "forwardPassMinGain": 15.0,
          "markDistance": 52.0,
          "passChanceDefault": 0.008100000210106373,
          "passChanceForward": 0.1453000009059906,
          "passChancePressured": 0.4000000059604645,
          "passChanceWing": 0.009999999776482582,
          "shootProgressThreshold": 0.8162999749183655,
          "tackleChance": 0.2199999988079071
        },
        "blockAvoidance": 0.37391412258148193,
        "blockDistance": 25.72054672241211,
        "chemistryBonus": 0.0,
        "chemistryTargetId": -1,
        "clearShotBonus": 0.06375373154878616,
        "corridorPreference": 0,
        "edgeAvoidance": 0.0,
        "goalAttraction": 0.26878899335861206,
        "pressureRadius": 95.31826782226562,
        "riskAppetite": 0.5823724269866943,
        "visionRadius": 1000000000.0,
        "zoneAggression": [
          0.8120741844177246,
          0.9085901379585266,
          1.0274022817611694,
          1.1917575597763062,
          1.1601442098617554
        ]
      },
      {
        "aggression": 1.872754693031311,
        "base": {
          "forwardPassMinGain": 18.0,
          "markDistance": 74.0,
          "passChanceDefault": 0.004999999888241291,
          "passChanceForward": 0.1599999964237213,
          "passChancePressured": 0.4000000059604645,
          "passChanceWing": 0.009999999776482582,
          "shootProgressThreshold": 0.8125,
          "tackleChance": 0.19050000607967377
        },
        "blockAvoidance": 0.20702996850013733,
        "blockDistance": 28.949831008911133,
        "chemistryBonus": 0.0,
        "chemistryTargetId": -1,
        "clearShotBonus": 0.2869267463684082,
        "corridorPreference": 1,
        "edgeAvoidance": 0.0,
        "goalAttraction": 0.6546172499656677,
        "pressureRadius": 61.78904342651367,
        "riskAppetite": 0.4824705123901367,
        "visionRadius": 1000000000.0,
        "zoneAggression": [
          1.086510419845581,
          1.5088210105895996,
          0.876882791519165,
          0.7904089689254761,
          1.085485816001892
        ]
      },
      {
        "aggression": 1.1845840215682983,
        "base": {
          "forwardPassMinGain": 11.0,
          "markDistance": 76.0,
          "passChanceDefault": 0.13689999282360077,
          "passChanceForward": 0.16009999811649323,
          "passChancePressured": 0.3255999982357025,
          "passChanceWing": 0.009999999776482582,
          "shootProgressThreshold": 0.6836000084877014,
          "tackleChance": 0.10719999670982361
        },
        "blockAvoidance": 0.5181546807289124,
        "blockDistance": 35.2830810546875,
        "chemistryBonus": 0.0,
        "chemistryTargetId": -1,
        "clearShotBonus": 0.17819565534591675,
        "corridorPreference": 0,
        "edgeAvoidance": 0.7821962237358093,
        "goalAttraction": 0.19522592425346375,
        "pressureRadius": 90.59664154052734,
        "riskAppetite": 0.007680416107177734,
        "visionRadius": 1000000000.0,
        "zoneAggression": [
          1.2757760286331177,
          1.0087579488754272,
          0.689176082611084,
          1.4844814538955688,
          0.8029693961143494
        ]
      },
      {
        "aggression": 1.271427869796753,
        "base": {
          "forwardPassMinGain": 14.0,
          "markDistance": 77.0,
          "passChanceDefault": 0.05290000140666962,
          "passChanceForward": 0.1543000042438507,
          "passChancePressured": 0.4000000059604645,
          "passChanceWing": 0.07020000368356705,
          "shootProgressThreshold": 0.8607000112533569,
          "tackleChance": 0.16120000183582306
        },
        "blockAvoidance": 0.6841490864753723,
        "blockDistance": 13.251578330993652,
        "chemistryBonus": 0.0,
        "chemistryTargetId": -1,
        "clearShotBonus": 0.4391512870788574,
        "corridorPreference": -1,
        "edgeAvoidance": 0.5564186573028564,
        "goalAttraction": 0.19854560494422913,
        "pressureRadius": 38.513702392578125,
        "riskAppetite": 0.29490405321121216,
        "visionRadius": 1000000000.0,
        "zoneAggression": [
          1.1172020435333252,
          0.9545609951019287,
          1.1811184883117676,
          1.055994987487793,
          0.7032451629638672
        ]
      }
    ],
    "sourceEpoch": 71
  },
  "session": "session-6"
}
