{
  "accepted": false,
  "candidate": {
    "parameters": {
      "forwardPassMinGain": 18.0,
      "markDistance": 73.0,
      "passChanceDefault": 0.09080000221729279,
      "passChanceForward": 0.12280000001192093,
      "passChancePressured": 0.4000000059604645,
      "passChanceWing": 0.009999999776482582,
      "shootProgressThreshold": 0.839900016784668,
      "tackleChance": 0.210999995470047
    }
  },
  "championEpoch": 524,
  "championParameters": {
    "forwardPassMinGain": 17.0,
    "markDistance": 73.0,
    "passChanceDefault": 0.08259999752044678,
    "passChanceForward": 0.1370999962091446,
    "passChancePressured": 0.37779998779296875,
    "passChanceWing": 0.010599999688565731,
    "shootProgressThreshold": 0.8138999938964844,
    "tackleChance": 0.210999995470047
  },
  "createdAt": "2026-04-30T09:59:53Z",
  "epoch": 529,
  "evaluation": {
    "avgGoals": 10.93,
    "avgOutOfBounds": 0.01,
    "avgPasses": 121.76,
    "avgShots": 44.57,
    "avgTackles": 6.09,
    "baselineAvgGoals": 5.745,
    "candidateAvgGoals": 5.185,
    "candidateWon": false,
    "earlyStop": "worse",
    "elapsedMs": 213,
    "games": 750,
    "gamesPerSecond": 3521.13,
    "goalDiff": -420.0,
    "maxGames": 1000,
    "passCompletionRate": 0.897,
    "tackleSuccessRate": 1.0,
    "zScore": -2.536
  },
  "gamesPerEpoch": 1000,
  "name": "epoch-529",
  "opponent": {
    "parameters": {
      "forwardPassMinGain": 17.0,
      "markDistance": 73.0,
      "passChanceDefault": 0.08259999752044678,
      "passChanceForward": 0.1370999962091446,
      "passChancePressured": 0.37779998779296875,
      "passChanceWing": 0.010599999688565731,
      "shootProgressThreshold": 0.8138999938964844,
      "tackleChance": 0.210999995470047
    },
    "sourceEpoch": 524
  },
  "session": "session-4"
}
