{
  "accepted": false,
  "candidate": {
    "parameters": {
      "forwardPassMinGain": 14.0,
      "markDistance": 71.0,
      "passChanceDefault": 0.004999999888241291,
      "passChanceForward": 0.16110000014305115,
      "passChancePressured": 0.4000000059604645,
      "passChanceWing": 0.01730000041425228,
      "shootProgressThreshold": 0.7498000264167786,
      "tackleChance": 0.2021999955177307
    }
  },
  "championEpoch": 998,
  "championParameters": {
    "forwardPassMinGain": 14.0,
    "markDistance": 68.0,
    "passChanceDefault": 0.012500000186264515,
    "passChanceForward": 0.1542000025510788,
    "passChancePressured": 0.4000000059604645,
    "passChanceWing": 0.01730000041425228,
    "shootProgressThreshold": 0.8133999705314636,
    "tackleChance": 0.2053000032901764
  },
  "createdAt": "2026-04-30T10:07:04Z",
  "epoch": 999,
  "evaluation": {
    "avgGoals": 2.4,
    "avgOutOfBounds": 0.0,
    "avgPasses": 102.55,
    "avgShots": 136.56,
    "avgTackles": 3.45,
    "baselineAvgGoals": 2.33,
    "candidateAvgGoals": 0.07,
    "candidateWon": false,
    "earlyStop": "worse",
    "elapsedMs": 32,
    "games": 100,
    "gamesPerSecond": 3125.0,
    "goalDiff": -226.0,
    "maxGames": 1000,
    "passCompletionRate": 0.973,
    "tackleSuccessRate": 1.0,
    "zScore": -7.601
  },
  "gamesPerEpoch": 1000,
  "name": "epoch-999",
  "opponent": {
    "parameters": {
      "forwardPassMinGain": 14.0,
      "markDistance": 68.0,
      "passChanceDefault": 0.012500000186264515,
      "passChanceForward": 0.1542000025510788,
      "passChancePressured": 0.4000000059604645,
      "passChanceWing": 0.01730000041425228,
      "shootProgressThreshold": 0.8133999705314636,
      "tackleChance": 0.2053000032901764
    },
    "sourceEpoch": 998
  },
  "session": "session-6"
}
